LICENSE.txt
MANIFEST.in
setup.py
lemon_tinymce.egg-info/PKG-INFO
lemon_tinymce.egg-info/SOURCES.txt
lemon_tinymce.egg-info/dependency_links.txt
lemon_tinymce.egg-info/not-zip-safe
lemon_tinymce.egg-info/top_level.txt
tinymce/__init__.py
tinymce/models.py
tinymce/settings.py
tinymce/urls.py
tinymce/views.py
tinymce/widgets.py
tinymce/static/tinymce/js/license.txt
tinymce/static/tinymce/js/tiny_mce.js
tinymce/static/tinymce/js/tiny_mce_filebrowser.js
tinymce/static/tinymce/js/tiny_mce_popup.js
tinymce/static/tinymce/js/tiny_mce_src.js
tinymce/static/tinymce/js/langs/en.js
tinymce/static/tinymce/js/langs/ru.js
tinymce/static/tinymce/js/plugins/advhr/editor_plugin.js
tinymce/static/tinymce/js/plugins/advhr/editor_plugin_src.js
tinymce/static/tinymce/js/plugins/advhr/rule.htm
tinymce/static/tinymce/js/plugins/advhr/css/advhr.css
tinymce/static/tinymce/js/plugins/advhr/js/rule.js
tinymce/static/tinymce/js/plugins/advhr/langs/en_dlg.js
tinymce/static/tinymce/js/plugins/advhr/langs/ru_dlg.js
tinymce/static/tinymce/js/plugins/advimage/editor_plugin.js
tinymce/static/tinymce/js/plugins/advimage/editor_plugin_src.js
tinymce/static/tinymce/js/plugins/advimage/image.htm
tinymce/static/tinymce/js/plugins/advimage/css/advimage.css
tinymce/static/tinymce/js/plugins/advimage/img/sample.gif
tinymce/static/tinymce/js/plugins/advimage/js/image.js
tinymce/static/tinymce/js/plugins/advimage/langs/en_dlg.js
tinymce/static/tinymce/js/plugins/advimage/langs/ru_dlg.js
tinymce/static/tinymce/js/plugins/advlink/editor_plugin.js
tinymce/static/tinymce/js/plugins/advlink/editor_plugin_src.js
tinymce/static/tinymce/js/plugins/advlink/link.htm
tinymce/static/tinymce/js/plugins/advlink/css/advlink.css
tinymce/static/tinymce/js/plugins/advlink/js/advlink.js
tinymce/static/tinymce/js/plugins/advlink/langs/en_dlg.js
tinymce/static/tinymce/js/plugins/advlink/langs/ru_dlg.js
tinymce/static/tinymce/js/plugins/advlist/editor_plugin.js
tinymce/static/tinymce/js/plugins/advlist/editor_plugin_src.js
tinymce/static/tinymce/js/plugins/autolink/editor_plugin.js
tinymce/static/tinymce/js/plugins/autolink/editor_plugin_src.js
tinymce/static/tinymce/js/plugins/autoresize/editor_plugin.js
