Metadata-Version: 1.0
Name: lemon-tinymce
Version: 2.1.1
Summary: A Django application that contains a widget to render a form field as a TinyMCE editor.
Home-page: https://github.com/trilan/lemon-tinymce
Author: Trilan Team
Author-email: dev@lemon.io
License: UNKNOWN
Platform: UNKNOWN
